ticketgenerator/__init__.py
ticketgenerator/housieticket.py
example_pkg_ksgsarma-0.0.1.dist-info/METADATA
example_pkg_ksgsarma-0.0.1.dist-info/WHEEL
example_pkg_ksgsarma-0.0.1.dist-info/top_level.txt
example_pkg_ksgsarma-0.0.1.dist-info/RECORD
